core/BotLogger.py
core/SimpleMenus.py
core/TextAnsiFormater.py
core/UserInput.py
core/UserOutput.py
core/__init__.py
core/__version__.py
smallapplib-1.2.0.dist-info/METADATA
smallapplib-1.2.0.dist-info/WHEEL
smallapplib-1.2.0.dist-info/top_level.txt
smallapplib-1.2.0.dist-info/RECORD
