Metadata-Version: 2.4
Name: SmallAppLib
Version: 1.2.0
Summary: App for simple console app building
Author: Cupcake_wrld
Author-email: evilprog@yandex.ru
Keywords: files small console
Classifier: Programming Language :: Python :: 3.12
Classifier: Operating System :: OS Independent
Requires-Python: >=3.12
Dynamic: author
Dynamic: author-email
Dynamic: classifier
Dynamic: description
Dynamic: description-content-type
Dynamic: keywords
Dynamic: requires-python
Dynamic: summary
